spec2flux/__init__.py
spec2flux/doppler_calculator.py
spec2flux/emission_lines.py
spec2flux/flux_calcator.py
spec2flux/input_check.py
spec2flux/model_fitter.py
spec2flux/plotter.py
spec2flux/spectrum_data.py
spec2flux-1.0.0.dist-info/LICENSE
spec2flux-1.0.0.dist-info/METADATA
spec2flux-1.0.0.dist-info/WHEEL
spec2flux-1.0.0.dist-info/top_level.txt
spec2flux-1.0.0.dist-info/RECORD
