Metadata-Version: 2.2
Name: spec2flux
Version: 1.0.0
Summary: Given a FITS spectrum file, this script fits a Voigt profile to each emission line, facilitating flux calculation and data validity assessment. It generates plots for each line and outputs comprehensive results in both FITS and ECSV formats. These files contain all necessary information for analysis or reproduction.
Home-page: https://github.com/bellalongo/spec2flux
Author: Bella Longo
Author-email: bellalongo.mail@gmail.com
Classifier: Development Status :: 3 - Alpha
Classifier: License :: OSI Approved :: MIT License
Classifier: Operating System :: OS Independent
Classifier: Programming Language :: Python :: 3
Classifier: Intended Audience :: Science/Research
License-File: LICENSE
Requires-Dist: matplotlib
Requires-Dist: astropy
Requires-Dist: scipy
Requires-Dist: seaborn
Requires-Dist: numpy<2.0.0,>=1.26.4
Requires-Dist: pandas
Requires-Dist: FuzzyTM>=0.4.0
Dynamic: author
Dynamic: author-email
Dynamic: classifier
Dynamic: description
Dynamic: description-content-type
Dynamic: home-page
Dynamic: requires-dist
Dynamic: summary
